[
    {
        "endpoint": "fixtures/statistics",
        "query": {
            "fixture": "1208124"
        },
        "response": {
            "get": "fixtures/statistics",
            "parameters": {
                "fixture": "1208124"
            },
            "errors": [],
            "results": 2,
            "paging": {
                "current": 1,
                "total": 1
            },
            "response": [
                {
                    "team": {
                        "id": 51,
                        "name": "Brighton",
                        "logo": "https://media.api-sports.io/football/teams/51.png"
                    },
                    "statistics": [
                        {
                            "type": "Shots on Goal",
                            "value": 4
                        },
                        {
                            "type": "Shots off Goal",
                            "value": 4
                        },
                        {
                            "type": "Total Shots",
                            "value": 10
                        },
                        {
                            "type": "Blocked Shots",
                            "value": 2
                        },
                        {
                            "type": "Shots insidebox",
                            "value": 8
                        },
                        {
                            "type": "Shots outsidebox",
                            "value": 2
                        },
                        {
                            "type": "Fouls",
                            "value": 12
                        },
                        {
                            "type": "Corner Kicks",
                            "value": 0
                        },
                        {
                            "type": "Offsides",
                            "value": 3
                        },
                        {
                            "type": "Ball Possession",
                            "value": "40%"
                        },
                        {
                            "type": "Yellow Cards",
                            "value": 3
                        },
                        {
                            "type": "Red Cards",
                            "value": null
                        },
                        {
                            "type": "Goalkeeper Saves",
                            "value": 5
                        },
                        {
                            "type": "Total passes",
                            "value": 426
                        },
                        {
                            "type": "Passes accurate",
                            "value": 372
                        },
                        {
                            "type": "Passes %",
                            "value": "87%"
                        },
                        {
                            "type": "expected_goals",
                            "value": "2.29"
                        },
                        {
                            "type": "goals_prevented",
                            "value": 0
                        }
                    ]
                },
                {
                    "team": {
                        "id": 50,
                        "name": "Manchester City",
                        "logo": "https://media.api-sports.io/football/teams/50.png"
                    },
                    "statistics": [
                        {
                            "type": "Shots on Goal",
                            "value": 6
                        },
                        {
                            "type": "Shots off Goal",
                            "value": 6
                        },
                        {
                            "type": "Total Shots",
                            "value": 15
                        },
                        {
                            "type": "Blocked Shots",
                            "value": 3
                        },
                        {
                            "type": "Shots insidebox",
                            "value": 12
                        },
                        {
                            "type": "Shots outsidebox",
                            "value": 3
                        },
                        {
                            "type": "Fouls",
                            "value": 10
                        },
                        {
                            "type": "Corner Kicks",
                            "value": 4
                        },
                        {
                            "type": "Offsides",
                            "value": 1
                        },
                        {
                            "type": "Ball Possession",
                            "value": "60%"
                        },
                        {
                            "type": "Yellow Cards",
                            "value": 3
                        },
                        {
                            "type": "Red Cards",
                            "value": null
                        },
                        {
                            "type": "Goalkeeper Saves",
                            "value": 2
                        },
                        {
                            "type": "Total passes",
                            "value": 653
                        },
                        {
                            "type": "Passes accurate",
                            "value": 586
                        },
                        {
                            "type": "Passes %",
                            "value": "90%"
                        },
                        {
                            "type": "expected_goals",
                            "value": "2.22"
                        },
                        {
                            "type": "goals_prevented",
                            "value": 0
                        }
                    ]
                }
            ]
        }
    }
]